ambiance_client/__init__.py
ambiance_client/ambiance_client.py
ambiance_client-0.0.3.dist-info/LICENSE.txt
ambiance_client-0.0.3.dist-info/METADATA
ambiance_client-0.0.3.dist-info/WHEEL
ambiance_client-0.0.3.dist-info/top_level.txt
ambiance_client-0.0.3.dist-info/RECORD
