Metadata-Version: 2.1
Name: ambiance-client
Version: 0.0.3
Summary: A Python client for the Elixir Ambiance home automation API
Home-page: https://gitlab.com/bklang/ambiance_client
Author: Ben Klang
Author-email: bklang@wirehack.net
License: UNKNOWN
Platform: UNKNOWN
Classifier: Programming Language :: Python :: 3
Classifier: License :: OSI Approved :: MIT License
Classifier: Operating System :: OS Independent
Requires-Python: >=3.6
Requires-Dist: requests
